{
  "RewardJsonVersion": "1.0.0",
  "Name": "Fishing",
  "DisplayName": "Fishing",
  "LevelDrainage": 50,
  "MaxLevel": 50,

  "Events": {
    "PlayerFishing": [
      {
        "TypeEntityName": ["COD"],
        "EXP": { "min": 10, "max": 20 },
        "PlayerGetExp": 0,
        "Chance": 100,
        "RequiredLevel": 0,
        "RequiredTools": [],
        "ExtraEXP": { "multiplier": 0.0, "bonusEXP": 0 },
        "UseAdvancedSettings": true,
        "AdvancedSettings": {
          "RequireDirectKill": true,
          "DisallowNamedEntity": true,
          "PreventXPGrinding": { "Radius": 8, "CooldownSeconds": 20 },
          "PlayerPermissionOverride": "hunting.bypass"
        }
      },
      {
        "TypeEntityName": ["SALMON"],
        "EXP": { "min": 12, "max": 22 },
        "PlayerGetExp": 0,
        "Chance": 100,
        "RequiredLevel": 0,
        "RequiredTools": [],
        "ExtraEXP": { "multiplier": 0.0, "bonusEXP": 0 },
        "UseAdvancedSettings": true,
        "AdvancedSettings": {
          "RequireDirectKill": true,
          "DisallowNamedEntity": true,
          "PreventXPGrinding": { "Radius": 8, "CooldownSeconds": 20 },
          "PlayerPermissionOverride": "hunting.bypass"
        }
      },
      {
        "TypeEntityName": ["PUFFERFISH"],
        "EXP": { "min": 20, "max": 35 },
        "PlayerGetExp": 0,
        "Chance": 100,
        "RequiredLevel": 0,
        "RequiredTools": [],
        "ExtraEXP": { "multiplier": 0.0, "bonusEXP": 0 },
        "UseAdvancedSettings": true,
        "AdvancedSettings": {
          "RequireDirectKill": true,
          "DisallowNamedEntity": true,
          "PreventXPGrinding": { "Radius": 8, "CooldownSeconds": 20 },
          "PlayerPermissionOverride": "hunting.bypass"
        }
      },
      {
        "TypeEntityName": ["TROPICAL_FISH"],
        "EXP": { "min": 22, "max": 40 },
        "PlayerGetExp": 0,
        "Chance": 100,
        "RequiredLevel": 0,
        "RequiredTools": [],
        "ExtraEXP": { "multiplier": 0.0, "bonusEXP": 0 },
        "UseAdvancedSettings": true,
        "AdvancedSettings": {
          "RequireDirectKill": true,
          "DisallowNamedEntity": true,
          "PreventXPGrinding": { "Radius": 8, "CooldownSeconds": 20 },
          "PlayerPermissionOverride": "hunting.bypass"
        }
      },
      {
        "TypeEntityName": ["GLOW_SQUID"],
        "EXP": { "min": 40, "max": 65 },
        "PlayerGetExp": 0,
        "Chance": 100,
        "RequiredLevel": 0,
        "RequiredTools": [],
        "ExtraEXP": { "multiplier": 0.0, "bonusEXP": 0 },
        "UseAdvancedSettings": true,
        "AdvancedSettings": {
          "RequireDirectKill": true,
          "DisallowNamedEntity": true,
          "PreventXPGrinding": { "Radius": 8, "CooldownSeconds": 20 },
          "PlayerPermissionOverride": "hunting.bypass"
        }
      },
      {
        "TypeEntityName": ["SQUID"],
        "EXP": { "min": 18, "max": 30 },
        "PlayerGetExp": 0,
        "Chance": 100,
        "RequiredLevel": 0,
        "RequiredTools": [],
        "ExtraEXP": { "multiplier": 0.0, "bonusEXP": 0 },
        "UseAdvancedSettings": true,
        "AdvancedSettings": {
          "RequireDirectKill": true,
          "DisallowNamedEntity": true,
          "PreventXPGrinding": { "Radius": 8, "CooldownSeconds": 20 },
          "PlayerPermissionOverride": "hunting.bypass"
        }
      },
      {
        "TypeEntityName": ["AXOLOTL"],
        "EXP": { "min": 70, "max": 120 },
        "PlayerGetExp": 0,
        "Chance": 100,
        "RequiredLevel": 0,
        "RequiredTools": [],
        "ExtraEXP": { "multiplier": 0.0, "bonusEXP": 0 },
        "UseAdvancedSettings": true,
        "AdvancedSettings": {
          "RequireDirectKill": true,
          "DisallowNamedEntity": true,
          "PreventXPGrinding": { "Radius": 10, "CooldownSeconds": 30 },
          "PlayerPermissionOverride": "hunting.bypass"
        }
      },
      {
        "TypeEntityName": ["BREEZE_FISH"],
        "EXP": { "min": 80, "max": 120 },
        "PlayerGetExp": 0,
        "Chance": 100,
        "RequiredLevel": 0,
        "RequiredTools": [],
        "ExtraEXP": { "multiplier": 0.0, "bonusEXP": 0 },
        "UseAdvancedSettings": true,
        "AdvancedSettings": {
          "RequireDirectKill": true,
          "DisallowNamedEntity": true,
          "PreventXPGrinding": { "Radius": 10, "CooldownSeconds": 30 },
          "PlayerPermissionOverride": "hunting.bypass"
        }
      },
      {
        "TypeEntityName": ["DRAGON_FISH"],
        "EXP": { "min": 90, "max": 120 },
        "PlayerGetExp": 0,
        "Chance": 100,
        "RequiredLevel": 0,
        "RequiredTools": [],
        "ExtraEXP": { "multiplier": 0.0, "bonusEXP": 0 },
        "UseAdvancedSettings": true,
        "AdvancedSettings": {
          "RequireDirectKill": true,
          "DisallowNamedEntity": true,
          "PreventXPGrinding": { "Radius": 10, "CooldownSeconds": 30 },
          "PlayerPermissionOverride": "hunting.bypass"
        }
      },
      {
        "TypeEntityName": ["OILY_FISH"],
        "EXP": { "min": 40, "max": 60 },
        "PlayerGetExp": 0,
        "Chance": 100,
        "RequiredLevel": 0,
        "RequiredTools": [],
        "ExtraEXP": { "multiplier": 0.0, "bonusEXP": 0 },
        "UseAdvancedSettings": true,
        "AdvancedSettings": {
          "RequireDirectKill": true,
          "DisallowNamedEntity": true,
          "PreventXPGrinding": { "Radius": 8, "CooldownSeconds": 20 },
          "PlayerPermissionOverride": "hunting.bypass"
        }
      },
      {
        "TypeEntityName": ["BONY_FISH"],
        "EXP": { "min": 35, "max": 55 },
        "PlayerGetExp": 0,
        "Chance": 100,
        "RequiredLevel": 0,
        "RequiredTools": [],
        "ExtraEXP": { "multiplier": 0.0, "bonusEXP": 0 },
        "UseAdvancedSettings": true,
        "AdvancedSettings": {
          "RequireDirectKill": true,
          "DisallowNamedEntity": true,
          "PreventXPGrinding": { "Radius": 8, "CooldownSeconds": 20 },
          "PlayerPermissionOverride": "hunting.bypass"
        }
      },
      {
        "TypeEntityName": ["SHIMMERING_FISH"],
        "EXP": { "min": 100, "max": 120 },
        "PlayerGetExp": 0,
        "Chance": 100,
        "RequiredLevel": 0,
        "RequiredTools": [],
        "ExtraEXP": { "multiplier": 0.0, "bonusEXP": 0 },
        "UseAdvancedSettings": true,
        "AdvancedSettings": {
          "RequireDirectKill": true,
          "DisallowNamedEntity": true,
          "PreventXPGrinding": { "Radius": 10, "CooldownSeconds": 30 },
          "PlayerPermissionOverride": "hunting.bypass"
        }
      }
    ],

    "KillEntity": [

      /* ================= KillEntity Events (이전과 동일하게 유지) ================= */

      {
        "TypeEntityName": ["COD"],
        "EXP": { "min": 10, "max": 20 },
        "PlayerGetExp": 0,
        "Chance": 100,
        "RequiredLevel": 0,
        "RequiredTools": [],
        "ExtraEXP": { "multiplier": 0.0, "bonusEXP": 0 },
        "UseAdvancedSettings": true,
        "AdvancedSettings": {
          "RequireDirectKill": true,
          "DisallowNamedEntity": true,
          "RequireNaturalSpawn": true,
          "PreventXPGrinding": { "Radius": 8, "CooldownSeconds": 20 },
          "PlayerPermissionOverride": "hunting.bypass"
        }
      },
      {
        "TypeEntityName": ["SALMON"],
        "EXP": { "min": 12, "max": 22 },
        "PlayerGetExp": 0,
        "Chance": 100,
        "RequiredLevel": 0,
        "RequiredTools": [],
        "ExtraEXP": { "multiplier": 0.0, "bonusEXP": 0 },
        "UseAdvancedSettings": true,
        "AdvancedSettings": {
          "RequireDirectKill": true,
          "DisallowNamedEntity": true,
          "RequireNaturalSpawn": true,
          "PreventXPGrinding": { "Radius": 8, "CooldownSeconds": 20 },
          "PlayerPermissionOverride": "hunting.bypass"
        }
      },
      {
        "TypeEntityName": ["PUFFERFISH"],
        "EXP": { "min": 20, "max": 35 },
        "PlayerGetExp": 0,
        "Chance": 100,
        "RequiredLevel": 0,
        "RequiredTools": [],
        "ExtraEXP": { "multiplier": 0.0, "bonusEXP": 0 },
        "UseAdvancedSettings": true,
        "AdvancedSettings": {
          "RequireDirectKill": true,
          "DisallowNamedEntity": true,
          "RequireNaturalSpawn": true,
          "PreventXPGrinding": { "Radius": 8, "CooldownSeconds": 20 },
          "PlayerPermissionOverride": "hunting.bypass"
        }
      },
      {
        "TypeEntityName": ["TROPICAL_FISH"],
        "EXP": { "min": 22, "max": 40 },
        "PlayerGetExp": 0,
        "Chance": 100,
        "RequiredLevel": 0,
        "RequiredTools": [],
        "ExtraEXP": { "multiplier": 0.0, "bonusEXP": 0 },
        "UseAdvancedSettings": true,
        "AdvancedSettings": {
          "RequireDirectKill": true,
          "DisallowNamedEntity": true,
          "RequireNaturalSpawn": true,
          "PreventXPGrinding": { "Radius": 8, "CooldownSeconds": 20 },
          "PlayerPermissionOverride": "hunting.bypass"
        }
      },
      {
        "TypeEntityName": ["GLOW_SQUID"],
        "EXP": { "min": 40, "max": 65 },
        "PlayerGetExp": 0,
        "Chance": 100,
        "RequiredLevel": 0,
        "RequiredTools": [],
        "ExtraEXP": { "multiplier": 0.0, "bonusEXP": 0 },
        "UseAdvancedSettings": true,
        "AdvancedSettings": {
          "RequireDirectKill": true,
          "DisallowNamedEntity": true,
          "RequireNaturalSpawn": true,
          "PreventXPGrinding": { "Radius": 8, "CooldownSeconds": 20 },
          "PlayerPermissionOverride": "hunting.bypass"
        }
      },
      {
        "TypeEntityName": ["SQUID"],
        "EXP": { "min": 18, "max": 30 },
        "PlayerGetExp": 0,
        "Chance": 100,
        "RequiredLevel": 0,
        "RequiredTools": [],
        "ExtraEXP": { "multiplier": 0.0, "bonusEXP": 0 },
        "UseAdvancedSettings": true,
        "AdvancedSettings": {
          "RequireDirectKill": true,
          "DisallowNamedEntity": true,
          "RequireNaturalSpawn": true,
          "PreventXPGrinding": { "Radius": 8, "CooldownSeconds": 20 },
          "PlayerPermissionOverride": "hunting.bypass"
        }
      },
      {
        "TypeEntityName": ["AXOLOTL"],
        "EXP": { "min": 70, "max": 120 },
        "PlayerGetExp": 0,
        "Chance": 100,
        "RequiredLevel": 0,
        "RequiredTools": [],
        "ExtraEXP": { "multiplier": 0.0, "bonusEXP": 0 },
        "UseAdvancedSettings": true,
        "AdvancedSettings": {
          "RequireDirectKill": true,
          "DisallowNamedEntity": true,
          "RequireNaturalSpawn": true,
          "PreventXPGrinding": { "Radius": 10, "CooldownSeconds": 30 },
          "PlayerPermissionOverride": "hunting.bypass"
        }
      },
      {
        "TypeEntityName": ["BREEZE_FISH"],
        "EXP": { "min": 80, "max": 120 },
        "PlayerGetExp": 0,
        "Chance": 100,
        "RequiredLevel": 0,
        "RequiredTools": [],
        "ExtraEXP": { "multiplier": 0.0, "bonusEXP": 0 },
        "UseAdvancedSettings": true,
        "AdvancedSettings": {
          "RequireDirectKill": true,
          "DisallowNamedEntity": true,
          "RequireNaturalSpawn": true,
          "PreventXPGrinding": { "Radius": 10, "CooldownSeconds": 30 },
          "PlayerPermissionOverride": "hunting.bypass"
        }
      },
      {
        "TypeEntityName": ["DRAGON_FISH"],
        "EXP": { "min": 90, "max": 120 },
        "PlayerGetExp": 0,
        "Chance": 100,
        "RequiredLevel": 0,
        "RequiredTools": [],
        "ExtraEXP": { "multiplier": 0.0, "bonusEXP": 0 },
        "UseAdvancedSettings": true,
        "AdvancedSettings": {
          "RequireDirectKill": true,
          "DisallowNamedEntity": true,
          "RequireNaturalSpawn": true,
          "PreventXPGrinding": { "Radius": 10, "CooldownSeconds": 30 },
          "PlayerPermissionOverride": "hunting.bypass"
        }
      },
      {
        "TypeEntityName": ["OILY_FISH"],
        "EXP": { "min": 40, "max": 60 },
        "PlayerGetExp": 0,
        "Chance": 100,
        "RequiredLevel": 0,
        "RequiredTools": [],
        "ExtraEXP": { "multiplier": 0.0, "bonusEXP": 0 },
        "UseAdvancedSettings": true,
        "AdvancedSettings": {
          "RequireDirectKill": true,
          "DisallowNamedEntity": true,
          "RequireNaturalSpawn": true,
          "PreventXPGrinding": { "Radius": 8, "CooldownSeconds": 20 },
          "PlayerPermissionOverride": "hunting.bypass"
        }
      },
      {
        "TypeEntityName": ["BONY_FISH"],
        "EXP": { "min": 35, "max": 55 },
        "PlayerGetExp": 0,
        "Chance": 100,
        "RequiredLevel": 0,
        "RequiredTools": [],
        "ExtraEXP": { "multiplier": 0.0, "bonusEXP": 0 },
        "UseAdvancedSettings": true,
        "AdvancedSettings": {
          "RequireDirectKill": true,
          "DisallowNamedEntity": true,
          "RequireNaturalSpawn": true,
          "PreventXPGrinding": { "Radius": 8, "CooldownSeconds": 20 },
          "PlayerPermissionOverride": "hunting.bypass"
        }
      },
      {
        "TypeEntityName": ["SHIMMERING_FISH"],
        "EXP": { "min": 100, "max": 120 },
        "PlayerGetExp": 0,
        "Chance": 100,
        "RequiredLevel": 0,
        "RequiredTools": [],
        "ExtraEXP": { "multiplier": 0.0, "bonusEXP": 0 },
        "UseAdvancedSettings": true,
        "AdvancedSettings": {
          "RequireDirectKill": true,
          "DisallowNamedEntity": true,
          "RequireNaturalSpawn": true,
          "PreventXPGrinding": { "Radius": 10, "CooldownSeconds": 30 },
          "PlayerPermissionOverride": "hunting.bypass"
        }
      }
    ]
  }
}
